alphaess_modbus/__init__.py
alphaess_modbus/formatter.py
alphaess_modbus/reader.py
alphaess_modbus/readertcp.py
alphaess_modbus/registers.json
alphaess_modbus-0.1.1.dist-info/LICENSE
alphaess_modbus-0.1.1.dist-info/WHEEL
alphaess_modbus-0.1.1.dist-info/METADATA
alphaess_modbus-0.1.1.dist-info/RECORD
