Metadata-Version: 2.1
Name: alphaess-modbus
Version: 0.1.1
Summary: Async Python 3 library to read ModBus from an AlphaESS inverter
Home-page: https://github.com/SorX14/alphaess_modbus
License: MIT
Keywords: python,alphaess,modbus,rs485,tcp,solar,pv
Author: steve.parker
Requires-Python: >=3.8,<4.0
Classifier: License :: OSI Approved :: MIT License
Classifier: Programming Language :: Python :: 3
Classifier: Programming Language :: Python :: 3.10
Classifier: Programming Language :: Python :: 3.8
Classifier: Programming Language :: Python :: 3.9
Requires-Dist: AsyncioMinimalModbus (>=1.0.0,<2.0.0)
Requires-Dist: pymodbus (>=3.0.2,<4.0.0)
Project-URL: Repository, https://github.com/SorX14/alphaess_modbus
